{
  "id": 2941,
  "split": "train",
  "name": "1350_E. Orac and Game of Life",
  "source": "codeforces",
  "difficulty": "E",
  "cf_contest_id": 1350,
  "cf_index": "E",
  "cf_points": 1250.0,
  "cf_rating": 2000,
  "cf_tags": [
    "dfs and similar",
    "graphs",
    "implementation",
    "shortest paths"
  ],
  "is_description_translated": false,
  "time_limit_seconds": 2.0,
  "memory_limit_bytes": 128000000,
  "input_file": "",
  "output_file": "",
  "counts": {
    "public_tests": 4,
    "private_tests": 3,
    "generated_tests": 52,
    "correct_solutions": 141,
    "incorrect_solutions": 145
  }
}
