{
  "id": 1612,
  "split": "train",
  "name": "518_D. Ilya and Escalator",
  "source": "codeforces",
  "difficulty": "D",
  "cf_contest_id": 518,
  "cf_index": "D",
  "cf_points": 2000.0,
  "cf_rating": 1700,
  "cf_tags": [
    "combinatorics",
    "dp",
    "math",
    "probabilities"
  ],
  "is_description_translated": false,
  "time_limit_seconds": 2.0,
  "memory_limit_bytes": 256000000,
  "input_file": "",
  "output_file": "",
  "counts": {
    "public_tests": 3,
    "private_tests": 35,
    "generated_tests": 56,
    "correct_solutions": 448,
    "incorrect_solutions": 358
  }
}
