{
  "id": 12869,
  "split": "train",
  "name": "869_C. The Intriguing Obsession",
  "source": "codeforces",
  "difficulty": "C",
  "cf_contest_id": 869,
  "cf_index": "C",
  "cf_points": 1500.0,
  "cf_rating": 1800,
  "cf_tags": [
    "combinatorics",
    "dp",
    "math"
  ],
  "is_description_translated": false,
  "time_limit_seconds": 1.0,
  "memory_limit_bytes": 256000000,
  "input_file": "",
  "output_file": "",
  "counts": {
    "public_tests": 4,
    "private_tests": 26,
    "generated_tests": 91,
    "correct_solutions": 399,
    "incorrect_solutions": 365
  }
}
