{
  "id": 7017,
  "split": "train",
  "name": "357_B. Flag Day",
  "source": "codeforces",
  "difficulty": "B",
  "cf_contest_id": 357,
  "cf_index": "B",
  "cf_points": 1000.0,
  "cf_rating": 1400,
  "cf_tags": [
    "constructive algorithms",
    "implementation"
  ],
  "is_description_translated": false,
  "time_limit_seconds": 1.0,
  "memory_limit_bytes": 256000000,
  "input_file": "",
  "output_file": "",
  "counts": {
    "public_tests": 3,
    "private_tests": 25,
    "generated_tests": 82,
    "correct_solutions": 714,
    "incorrect_solutions": 566
  }
}
