{
  "id": 7952,
  "split": "train",
  "name": "330_B. Road Construction",
  "source": "codeforces",
  "difficulty": "B",
  "cf_contest_id": 330,
  "cf_index": "B",
  "cf_points": 1000.0,
  "cf_rating": 1300,
  "cf_tags": [
    "constructive algorithms",
    "graphs"
  ],
  "is_description_translated": false,
  "time_limit_seconds": 2.0,
  "memory_limit_bytes": 256000000,
  "input_file": "",
  "output_file": "",
  "counts": {
    "public_tests": 1,
    "private_tests": 30,
    "generated_tests": 100,
    "correct_solutions": 905,
    "incorrect_solutions": 690
  }
}
