{
  "id": 1715,
  "split": "train",
  "name": "500_E. New Year Domino",
  "source": "codeforces",
  "difficulty": "E",
  "cf_contest_id": 500,
  "cf_index": "E",
  "cf_points": 2750.0,
  "cf_rating": 2300,
  "cf_tags": [
    "data structures",
    "dp",
    "dsu"
  ],
  "is_description_translated": false,
  "time_limit_seconds": 2.0,
  "memory_limit_bytes": 256000000,
  "input_file": "",
  "output_file": "",
  "counts": {
    "public_tests": 1,
    "private_tests": 9,
    "generated_tests": 44,
    "correct_solutions": 273,
    "incorrect_solutions": 544
  }
}
