{
  "id": 9393,
  "split": "train",
  "name": "1326_A. Bad Ugly Numbers",
  "source": "codeforces",
  "difficulty": "A",
  "cf_contest_id": 1326,
  "cf_index": "A",
  "cf_points": 500.0,
  "cf_rating": 1000,
  "cf_tags": [
    "constructive algorithms",
    "number theory"
  ],
  "is_description_translated": false,
  "time_limit_seconds": 1.0,
  "memory_limit_bytes": 256000000,
  "input_file": "",
  "output_file": "",
  "counts": {
    "public_tests": 1,
    "private_tests": 24,
    "generated_tests": 67,
    "correct_solutions": 1648,
    "incorrect_solutions": 607
  }
}
