{
  "id": 8894,
  "split": "train",
  "name": "453_E. Little Pony and Lord Tirek",
  "source": "codeforces",
  "difficulty": "E",
  "cf_contest_id": 453,
  "cf_index": "E",
  "cf_points": 2500.0,
  "cf_rating": 3100,
  "cf_tags": [
    "data structures"
  ],
  "is_description_translated": false,
  "time_limit_seconds": 3.0,
  "memory_limit_bytes": 256000000,
  "input_file": "",
  "output_file": "",
  "counts": {
    "public_tests": 1,
    "private_tests": 6,
    "generated_tests": 38,
    "correct_solutions": 171,
    "incorrect_solutions": 278
  }
}
