{
  "id": 3995,
  "split": "train",
  "name": "248_E. Piglet's Birthday",
  "source": "codeforces",
  "difficulty": "E",
  "cf_contest_id": 248,
  "cf_index": "E",
  "cf_points": 2500.0,
  "cf_rating": 2600,
  "cf_tags": [
    "dp",
    "math",
    "probabilities"
  ],
  "is_description_translated": false,
  "time_limit_seconds": 2.0,
  "memory_limit_bytes": 256000000,
  "input_file": "",
  "output_file": "",
  "counts": {
    "public_tests": 1,
    "private_tests": 8,
    "generated_tests": 63,
    "correct_solutions": 94,
    "incorrect_solutions": 192
  }
}
