{
  "id": 3452,
  "split": "train",
  "name": "1173_F. Nauuo and Portals",
  "source": "codeforces",
  "difficulty": "F",
  "cf_contest_id": 1173,
  "cf_index": "F",
  "cf_points": 1750.0,
  "cf_rating": 2900,
  "cf_tags": [
    "constructive algorithms"
  ],
  "is_description_translated": false,
  "time_limit_seconds": 2.0,
  "memory_limit_bytes": 256000000,
  "input_file": "",
  "output_file": "",
  "counts": {
    "public_tests": 2,
    "private_tests": 113,
    "generated_tests": 0,
    "correct_solutions": 39,
    "incorrect_solutions": 20
  }
}
