{
  "id": 13231,
  "split": "train",
  "name": "1032_D. Barcelonian Distance",
  "source": "codeforces",
  "difficulty": "D",
  "cf_contest_id": 1032,
  "cf_index": "D",
  "cf_points": 2000.0,
  "cf_rating": 1900,
  "cf_tags": [
    "geometry",
    "implementation"
  ],
  "is_description_translated": false,
  "time_limit_seconds": 1.0,
  "memory_limit_bytes": 256000000,
  "input_file": "",
  "output_file": "",
  "counts": {
    "public_tests": 2,
    "private_tests": 35,
    "generated_tests": 72,
    "correct_solutions": 137,
    "incorrect_solutions": 160
  }
}
