{
  "id": 1053,
  "split": "train",
  "name": "1091_H. New Year and the Tricolore Recreation",
  "source": "codeforces",
  "difficulty": "H",
  "cf_contest_id": 1091,
  "cf_index": "H",
  "cf_points": 4000.0,
  "cf_rating": 3200,
  "cf_tags": [
    "games"
  ],
  "is_description_translated": false,
  "time_limit_seconds": 4.0,
  "memory_limit_bytes": 256000000,
  "input_file": "",
  "output_file": "",
  "counts": {
    "public_tests": 3,
    "private_tests": 12,
    "generated_tests": 100,
    "correct_solutions": 29,
    "incorrect_solutions": 130
  }
}
