{
  "id": 4801,
  "split": "train",
  "name": "105_D. Entertaining Geodetics",
  "source": "codeforces",
  "difficulty": "D",
  "cf_contest_id": 105,
  "cf_index": "D",
  "cf_points": 2000.0,
  "cf_rating": 2700,
  "cf_tags": [
    "brute force",
    "dsu",
    "implementation"
  ],
  "is_description_translated": false,
  "time_limit_seconds": 1.0,
  "memory_limit_bytes": 256000000,
  "input_file": "",
  "output_file": "",
  "counts": {
    "public_tests": 1,
    "private_tests": 9,
    "generated_tests": 56,
    "correct_solutions": 76,
    "incorrect_solutions": 253
  }
}
