{
  "id": 655,
  "split": "train",
  "name": "1543_B. Customising the Track",
  "source": "codeforces",
  "difficulty": "B",
  "cf_contest_id": 1543,
  "cf_index": "B",
  "cf_points": 750.0,
  "cf_rating": 900,
  "cf_tags": [
    "combinatorics",
    "greedy",
    "math"
  ],
  "is_description_translated": false,
  "time_limit_seconds": 1.0,
  "memory_limit_bytes": 256000000,
  "input_file": "",
  "output_file": "",
  "counts": {
    "public_tests": 1,
    "private_tests": 0,
    "generated_tests": 100,
    "correct_solutions": 407,
    "incorrect_solutions": 263
  }
}
