{
  "id": 1931,
  "split": "train",
  "name": "682_D. Alyona and Strings",
  "source": "codeforces",
  "difficulty": "D",
  "cf_contest_id": 682,
  "cf_index": "D",
  "cf_points": 2000.0,
  "cf_rating": 1900,
  "cf_tags": [
    "dp",
    "strings"
  ],
  "is_description_translated": false,
  "time_limit_seconds": 2.0,
  "memory_limit_bytes": 256000000,
  "input_file": "",
  "output_file": "",
  "counts": {
    "public_tests": 2,
    "private_tests": 21,
    "generated_tests": 52,
    "correct_solutions": 430,
    "incorrect_solutions": 629
  }
}
