{
  "id": 5632,
  "split": "train",
  "name": "1011_B. Planning The Expedition",
  "source": "codeforces",
  "difficulty": "B",
  "cf_contest_id": 1011,
  "cf_index": "B",
  "cf_points": 1000.0,
  "cf_rating": 1200,
  "cf_tags": [
    "binary search",
    "brute force",
    "implementation"
  ],
  "is_description_translated": false,
  "time_limit_seconds": 1.0,
  "memory_limit_bytes": 256000000,
  "input_file": "",
  "output_file": "",
  "counts": {
    "public_tests": 4,
    "private_tests": 27,
    "generated_tests": 86,
    "correct_solutions": 736,
    "incorrect_solutions": 537
  }
}
